{
	"system" : {
		"platform" : "windows64",
		"os_name" : "Windows 10",
		"os_version" : "10.0"
	},
	"error" : {
		"executable" : "quartus",
		"comment" : "not_applicable",
		"error_message" : "Access Violation at 0X00007FFE87973280",
		"source_file" : "unknown",
		"line" : "0",
		"stack_trace" : "\t0x7ffe8797327f: db_rdb + 0x4327f (?update_sub_pointers@RDB_REPORT_HANDLER@@AEAAXPEAVRDB_FOLDER_OBJECT@@AEBV?$basic_string@DU?$char_traits@D@std@@V?$allocator@D@2@@std@@@Z + 0xbf)\n\t0x7ffe879732e0: db_rdb + 0x432e0 (?update_sub_pointers@RDB_REPORT_HANDLER@@AEAAXPEAVRDB_FOLDER_OBJECT@@AEBV?$basic_string@DU?$char_traits@D@std@@V?$allocator@D@2@@std@@@Z + 0x120)\n\t0x7ffe879384ef: db_rdb + 0x84ef (?get_report@RDB_REPORT@@SAPEAV1@AEBV?$basic_string@DU?$char_traits@D@std@@V?$allocator@D@2@@std@@0PEBVRDB_OBJECT@@@Z + 0x2bf)\n\t0x7ffe879385d9: db_rdb + 0x85d9 (?get_report@RDB_REPORT@@SAPEAV1@AEBV?$basic_string@DU?$char_traits@D@std@@V?$allocator@D@2@@std@@W4RDB_REPORT_TYPE@@PEBVRDB_OBJECT@@@Z + 0x79)\n\t0x7ffea176696b: DB_DBMUI + 0x696b (?get_rdb_report@DBMUI_MANAGER@@QEAAPEAVRDB_REPORT@@PEBDW4RDB_REPORT_TYPE@@0V?$QHD_ENUM_IMPL@UTYPE_BASE@QHD_STATE@@@@_N@Z + 0x56b)\n\t0x7ffe3ff5714f: resr_rpwq + 0x2714f (?load_report@RPWQ_REPORT_TOC_VIEW@@QEAAX_NPEBD@Z + 0x19f)\n\t0x7ffe3ff39323: resr_rpwq + 0x9323 (?do_load_report@RPWQ_FRAME_WND@@IEAA_N_NAEBVQString@@@Z + 0x63)\n\t0x7ffe3ff3b0bf: resr_rpwq + 0xb0bf (?on_rdb_cache_freed@RPWQ_FRAME_WND@@QEAAXXZ + 0x7f)\n\t0x7ffe3ff40ffc: resr_rpwq + 0x10ffc (?on_rdb_cache_freed@RPWQ_NTFQ_HANDLER@@QEAA_N_K_N@Z + 0xc)\n\t0x7ffea5f02050: ccl_ntfq + 0x2050 (?dispatch_notify_msg@NTFQ_NOTIFY_TARGET@@IEAA_NPEBVNTFQ_NOTIFY_MAP@@I_K_N@Z + 0x60)\n\t0x7ffea5f0210b: ccl_ntfq + 0x210b (?on_ntfq_notify@NTFQ_NOTIFY_TARGET@@UEAA_NI_K_N@Z + 0x3b)\n\t0x7ffea5f02c71: ccl_ntfq + 0x2c71 (?broadcast_notify@NTFQ_NOTIFY_MGR@@UEAA_NI_K@Z + 0xb1)\n\t0x7ffea17670d6: DB_DBMUI + 0x70d6 (?on_rdb_updated@DBMUI_MANAGER@@QEAA_N_K_N@Z + 0x56)\n\t0x7ffea5f02050: ccl_ntfq + 0x2050 (?dispatch_notify_msg@NTFQ_NOTIFY_TARGET@@IEAA_NPEBVNTFQ_NOTIFY_MAP@@I_K_N@Z + 0x60)\n\t0x7ffea5f0210b: ccl_ntfq + 0x210b (?on_ntfq_notify@NTFQ_NOTIFY_TARGET@@UEAA_NI_K_N@Z + 0x3b)\n\t0x7ffea5f02c71: ccl_ntfq + 0x2c71 (?broadcast_notify@NTFQ_NOTIFY_MGR@@UEAA_NI_K@Z + 0xb1)\n\t0x7ffe9a2f4d97: sys_flow + 0x34d97 (?refresh@FLOW_STATUS@@QEAAXXZ + 0x27)\n\t0x7ffe9a2f3108: sys_flow + 0x33108 (flow_refresh_report + 0x78)\n\t 0x73a94410: tcl86 + 0x14410 (TclInvokeStringCommand + 0xf0)\n\t 0x73a961e2: tcl86 + 0x161e2 (TclNRRunCallbacks + 0x62)\n\t 0x73a97a65: tcl86 + 0x17a65 (TclEvalEx + 0xa65)\n\t 0x73a98257: tcl86 + 0x18257 (Tcl_Eval + 0x37)\n\t 0x73a9958f: tcl86 + 0x1958f (Tcl_GlobalEval + 0x2f)\n\t0x7ffe8f14e10d: ccl_atcl + 0xe10d (?atcl_flush_queue@@YAX_N0@Z + 0x18d)\n\t 0x73ffc420: QtCore4 + 0x11c420 (?activate@QMetaObject@@SAXPEAVQObject@@PEBU1@HPEAPEAX@Z + 0x520)\n\t 0x73fff979: QtCore4 + 0x11f979 (?event@QObject@@UEAA_NPEAVQEvent@@@Z + 0x69)\n\t 0x73102e95: QtGui4 + 0x22e95 (?notify_helper@QApplicationPrivate@@QEAA_NPEAVQObject@@PEAVQEvent@@@Z + 0xf5)\n\t 0x73102b2f: QtGui4 + 0x22b2f (?notify@QApplication@@UEAA_NPEAVQObject@@PEAVQEvent@@@Z + 0x17bf)\n\t 0x73fed92b: QtCore4 + 0x10d92b (?notifyInternal@QCoreApplication@@AEAA_NPEAVQObject@@PEAVQEvent@@@Z + 0x7b)\n\t 0x74013b5d: QtCore4 + 0x133b5d (?registeredTimers@QEventDispatcherWin32@@UEBA?AV?$QList@U?$QPair@HH@@@@PEAVQObject@@@Z + 0x59d)\n\t 0x74012f7f: QtCore4 + 0x132f7f (?processEvents@QEventDispatcherWin32@@UEAA_NV?$QFlags@W4ProcessEventsFlag@QEventLoop@@@@@Z + 0xb5f)\n\t0x7ffeab7a8240: USER32 + 0x18240 (DispatchMessageW + 0x740)\n\t0x7ffeab7a7d00: USER32 + 0x17d00 (DispatchMessageW + 0x200)\n\t 0x74012802: QtCore4 + 0x132802 (?processEvents@QEventDispatcherWin32@@UEAA_NV?$QFlags@W4ProcessEventsFlag@QEventLoop@@@@@Z + 0x3e2)\n\t 0x73160eb4: QtGui4 + 0x80eb4 (?openPopup@QApplicationPrivate@@QEAAXPEAVQWidget@@@Z + 0x204)\n\t 0x73fedf79: QtCore4 + 0x10df79 (?processEvents@QCoreApplication@@SAXV?$QFlags@W4ProcessEventsFlag@QEventLoop@@@@@Z + 0x49)\n\t0x7ffe9a553726: SYS_QUI + 0x13726 (qui_call_app_process_event + 0x36)\n\t0x7ffe8ee01533: ccl_thr + 0x1533 (thr_qt_process_events + 0x43)\n\t0x7ffe9a2c4f54: sys_flow + 0x4f54 (?flow_call_cmd@@YA?AW4GEN_EXE_RETURN_CODE@@PEAVFLOW_FACADE@@PEBD@Z + 0x274)\n\t0x7ffe9a2d4d60: sys_flow + 0x14d60 (?flow_generic_call@@YA?AW4GEN_EXE_RETURN_CODE@@PEAVFLOW_FACADE@@PEBD1_N@Z + 0x1b0)\n\t0x7ffe9a2dc306: sys_flow + 0x1c306 (?flow_do_asm_portion@@YA?AW4GEN_EXE_RETURN_CODE@@PEAVFLOW_FACADE@@W4SMART_ACTION@HDB_NAMESPACE@@_N2@Z + 0x86)\n\t0x7ffe9a2e27c3: sys_flow + 0x227c3 (?flow_full_compile_or_simulate@@YA?AW4GEN_EXE_RETURN_CODE@@PEAVFLOW_FACADE@@UFLOW_INFO@@_NPEAV?$vector@V?$basic_string@DU?$char_traits@D@std@@V?$allocator@D@2@@std@@V?$allocator@V?$basic_string@DU?$char_traits@D@std@@V?$allocator@D@2@@std@@@2@@std@@@Z + 0x1ee3)\n\t0x7ffe9a2e3b7d: sys_flow + 0x23b7d (?flow_compile@@YA?AW4GEN_EXE_RETURN_CODE@@PEAVFLOW_FACADE@@UFLOW_INFO@@@Z + 0x2d)\n\t0x7ffe9a2da844: sys_flow + 0x1a844 (flow_execute_custom + 0x834)\n\t0x7ffe9a2d9fc9: sys_flow + 0x19fc9 (flow_execute + 0x39)\n\t0x7ffe9a5513f0: SYS_QUI + 0x113f0 (?on_start_flow@QUI_APP@@MEAA?AW4GEN_EXE_RETURN_CODE@@HVQString@@@Z + 0x420)\n\t0x7ffe9a596655: SYS_QUI + 0x56655 (?qt_static_metacall@QUI_APP@@CAXPEAVQObject@@W4Call@QMetaObject@@HPEAPEAX@Z + 0xa5)\n\t 0x73fff9f7: QtCore4 + 0x11f9f7 (?event@QObject@@UEAA_NPEAVQEvent@@@Z + 0xe7)\n\t 0x730fe57d: QtGui4 + 0x1e57d (?event@QApplication@@MEAA_NPEAVQEvent@@@Z + 0x38d)\n\t 0x73102e95: QtGui4 + 0x22e95 (?notify_helper@QApplicationPrivate@@QEAA_NPEAVQObject@@PEAVQEvent@@@Z + 0xf5)\n\t 0x73102b2f: QtGui4 + 0x22b2f (?notify@QApplication@@UEAA_NPEAVQObject@@PEAVQEvent@@@Z + 0x17bf)\n\t 0x73fed92b: QtCore4 + 0x10d92b (?notifyInternal@QCoreApplication@@AEAA_NPEAVQObject@@PEAVQEvent@@@Z + 0x7b)\n\t 0x73fef502: QtCore4 + 0x10f502 (?sendPostedEvents@QCoreApplicationPrivate@@SAXPEAVQObject@@HPEAVQThreadData@@@Z + 0x2b2)\n\t 0x74012fb8: QtCore4 + 0x132fb8 (?processEvents@QEventDispatcherWin32@@UEAA_NV?$QFlags@W4ProcessEventsFlag@QEventLoop@@@@@Z + 0xb98)\n\t0x7ffeab7a8240: USER32 + 0x18240 (DispatchMessageW + 0x740)\n\t0x7ffeab7a7d00: USER32 + 0x17d00 (DispatchMessageW + 0x200)\n\t 0x74012802: QtCore4 + 0x132802 (?processEvents@QEventDispatcherWin32@@UEAA_NV?$QFlags@W4ProcessEventsFlag@QEventLoop@@@@@Z + 0x3e2)\n\t 0x73160eb4: QtGui4 + 0x80eb4 (?openPopup@QApplicationPrivate@@QEAAXPEAVQWidget@@@Z + 0x204)\n\t 0x73fea88b: QtCore4 + 0x10a88b (?exec@QEventLoop@@QEAAHV?$QFlags@W4ProcessEventsFlag@QEventLoop@@@@@Z + 0x22b)\n\t 0x73fece6f: QtCore4 + 0x10ce6f (?exec@QCoreApplication@@SAHXZ + 0xdf)\n\t0x7ff63645197b: quartus + 0x197b (?qgq_main@@YAHHPEAPEBD@Z + 0x7b)\n\t0x7ffe8f412e98: CCL_MSG + 0x12e98 (?msg_main_thread@@YAPEAXPEAX@Z + 0x18)\n\t0x7ffe8f41467e: CCL_MSG + 0x1467e (?msg_thread_wrapper@@YAPEAXP6APEAXPEAX@Z0@Z + 0x6e)\n\t0x7ffe8f516660: ccl_mem + 0x16660 (?mem_thread_wrapper@@YAPEAXP6APEAXPEAX@Z0@Z + 0x70)\n\t0x7ffe8f412761: CCL_MSG + 0x12761 (?msg_exe_main@@YAHHPEAPEBDP6AHH0@Z@Z + 0xa1)\n\t0x7ff6364524e7: quartus + 0x24e7 (WinMain + 0x127)\n\t0x7ff636451e58: quartus + 0x1e58 (__tmainCRTStartup + 0x148)\n\t0x7ffeab21257c: KERNEL32 + 0x1257c (BaseThreadInitThunk + 0x1c)\n\t0x7ffeabd4aa57: ntdll + 0x5aa57 (RtlUserThreadStart + 0x27)\n",
		"subsystem" : "unknown"
	},
	"quartus" : {
		"quartus_bits" : "64",
		"version" : "18.1.0",
		"build" : "625",
		"edition" : "Lite Edition"
	}
}